{
  "$schema": "https://gitee.com/dotnetchina/Furion/raw/v4/schemas/v4/furion-schema.json",

  "SpecificationDocumentSettings": {
    "DocumentTitle": "Admin",
    "GroupOpenApiInfos": [
      {
        "Group": "Default",
        "Title": "后端接口",
        "Description": "",
        "Version": "1.0.0",
        "TermsOfService": "#",
        "Contact": {
          "Name": "123",
          "Email": "123@qq.com",
          "Url": "#"
        },
        "Order": 1
      },
      {
        "Group": "Bus",
        "Title": "后端业务接口",
        "Description": "",
        "Version": "1.0.0",
        "TermsOfService": "#",
        "Contact": {
          "Name": "123",
          "Email": "123@qq.com",
          "Url": "#"
        },
        "Order": 2
      },
      {
        "Group": "Front",
        "Title": "前端接口",
        "Description": "",
        "Version": "1.0.0",
        "TermsOfService": "#",
        "Contact": {
          "Name": "123",
          "Email": "123@qq.com",
          "Url": "#"
        },
        "Order": 3
      },
      {
        "Group": "All Groups",
        "Title": "所有接口",
        "Description": "",
        "Version": "1.0.0",
        "TermsOfService": "#",
        "Contact": {
          "Name": "123",
          "Email": "123@qq.com",
          "Url": "#"
        },
        "Order": 0
      }
    ],
    "DefaultGroupName": "Default", // 默认分组名
    "DocExpansionState": "List", // List、Full、None
    "EnableAllGroups": false,
    "LoginInfo": {
      "Enabled": true, // 是否开启Swagger登录
      "CheckUrl": "/swagger/checkUrl",
      "SubmitUrl": "/swagger/submitUrl"
    },
    "EnumToNumber": true // 枚举类型生成值类型
  }
}